pidconnectioninfos/README.MD
pidconnectioninfos/__init__.py
pidconnectioninfos/requirements.txt
pidconnectioninfos/thirdparty.json
pidconnectioninfos-0.10.dist-info/LICENSE.rst
pidconnectioninfos-0.10.dist-info/METADATA
pidconnectioninfos-0.10.dist-info/WHEEL
pidconnectioninfos-0.10.dist-info/top_level.txt
pidconnectioninfos-0.10.dist-info/RECORD
