Metadata-Version: 2.1
Name: pidconnectioninfos
Version: 0.10
Summary: Finds processes holding files/ports open, as well as all generations of children
Home-page: https://github.com/hansalemaos/pidconnectioninfos
Author: Johannes Fischer
Author-email: aulasparticularesdealemaosp@gmail.com
License: MIT
Keywords: process,data
Classifier: Development Status :: 4 - Beta
Classifier: Programming Language :: Python :: 3 :: Only
Classifier: Programming Language :: Python :: 3.10
Classifier: Topic :: Software Development :: Libraries :: Python Modules
Classifier: Topic :: Utilities
License-File: LICENSE.rst
Requires-Dist: flatten-any-dict-iterable-or-whatsoever
